zodbpickle/__init__.py
zodbpickle/_pickle.cpython-38-darwin.so
zodbpickle/_pickle_33.c
zodbpickle/fastpickle.py
zodbpickle/pickle.py
zodbpickle/pickle_3.py
zodbpickle/pickletools_3.py
zodbpickle/slowpickle.py
zodbpickle/tests/__init__.py
zodbpickle/tests/pickle_3_tests.py
zodbpickle/tests/pickletester_3.py
zodbpickle/tests/test_compile_flags.py
zodbpickle/tests/test_pickle.py
zodbpickle-4.1.1.dist-info/LICENSE.txt
zodbpickle-4.1.1.dist-info/METADATA
zodbpickle-4.1.1.dist-info/WHEEL
zodbpickle-4.1.1.dist-info/top_level.txt
zodbpickle-4.1.1.dist-info/RECORD
