Metadata-Version: 2.1
Name: zodbpickle
Version: 4.1.1
Summary: Fork of Python 3 pickle module.
Home-page: https://github.com/zopefoundation/zodbpickle
Author: Python and Zope Foundation
Author-email: zodb-dev@zope.dev
License: PSFL 2 and ZPL 2.1
Keywords: zodb pickle
Platform: any
Classifier: Development Status :: 5 - Production/Stable
Classifier: License :: OSI Approved :: Zope Public License
Classifier: License :: OSI Approved :: Python Software Foundation License
Classifier: Programming Language :: Python
Classifier: Programming Language :: Python :: 3
Classifier: Programming Language :: Python :: 3.8
Classifier: Programming Language :: Python :: 3.9
Classifier: Programming Language :: Python :: 3.10
Classifier: Programming Language :: Python :: 3.11
Classifier: Programming Language :: Python :: 3.12
Classifier: Programming Language :: Python :: 3.13
Classifier: Programming Language :: Python :: Implementation :: CPython
Classifier: Programming Language :: Python :: Implementation :: PyPy
Classifier: Framework :: ZODB
Classifier: Topic :: Database
Classifier: Topic :: Software Development :: Libraries :: Python Modules
Classifier: Operating System :: Microsoft :: Windows
Classifier: Operating System :: Unix
Classifier: Operating System :: MacOS :: MacOS X
Requires-Python: >=3.8
License-File: LICENSE.txt
Requires-Dist: setuptools
Provides-Extra: docs
Requires-Dist: Sphinx; extra == "docs"
Provides-Extra: test
Requires-Dist: zope.testrunner; extra == "test"
